{
  "fields": {
    "apiVersion": {
      "label": "apiVersion",
      "order": 1,
      "type": "text"
    },
    "kind": {
      "label": "kind",
      "order": 0,
      "type": "text"
    },
    "metadata": {
      "fields": {
        "annotations": {
          "items": {
            "fields": {
              "_key": {
                "label": "key",
                "type": "text"
              },
              "val": {
                "label": "val",
                "type": "text"
              }
            },
            "type": "object"
          },
          "label": "annotations",
          "order": 11,
          "type": "map"
        },
        "creationTimestamp": {
          "label": "creationTimestamp",
          "order": 7,
          "type": "text"
        },
        "deletionGracePeriodSeconds": {
          "label": "deletionGracePeriodSeconds",
          "order": 9,
          "type": "text"
        },
        "deletionTimestamp": {
          "label": "deletionTimestamp",
          "order": 8,
          "type": "text"
        },
        "generateName": {
          "label": "generateName",
          "order": 1,
          "type": "text"
        },
        "generation": {
          "label": "generation",
          "order": 6,
          "type": "text"
        },
        "labels": {
          "items": {
            "fields": {
              "_key": {
                "label": "key",
                "type": "text"
              },
              "val": {
                "label": "val",
                "type": "text"
              }
            },
            "type": "object"
          },
          "label": "labels",
          "order": 10,
          "type": "map"
        },
        "name": {
          "label": "name",
          "order": 0,
          "type": "text"
        },
        "namespace": {
          "label": "namespace",
          "order": 2,
          "type": "text"
        },
        "resourceVersion": {
          "label": "resourceVersion",
          "order": 5,
          "type": "text"
        },
        "selfLink": {
          "label": "selfLink",
          "order": 3,
          "type": "text"
        },
        "uid": {
          "label": "uid",
          "order": 4,
          "type": "text"
        }
      },
      "label": "metadata",
      "order": 2
    },
    "spec": {
      "fields": {
        "accessModes": {
          "items": {
            "fields": {}
          },
          "label": "accessModes",
          "order": 14
        },
        "awsElasticBlockStore": {
          "fields": {
            "fsType": {
              "label": "fsType",
              "order": 1,
              "type": "text"
            },
            "partition": {
              "label": "partition",
              "order": 2,
              "type": "text"
            },
            "readOnly": {
              "label": "readOnly",
              "order": 3,
              "type": "text"
            },
            "volumeID": {
              "label": "volumeID",
              "order": 0,
              "type": "text"
            }
          },
          "label": "awsElasticBlockStore",
          "order": 2
        },
        "azureFile": {
          "fields": {
            "readOnly": {
              "label": "readOnly",
              "order": 2,
              "type": "text"
            },
            "secretName": {
              "label": "secretName",
              "order": 0,
              "type": "text"
            },
            "shareName": {
              "label": "shareName",
              "order": 1,
              "type": "text"
            }
          },
          "label": "azureFile",
          "order": 13
        },
        "capacity": {
          "items": {
            "fields": {
              "_key": {
                "label": "key",
                "type": "text"
              },
              "val": {
                "label": "val",
                "type": "text"
              }
            },
            "type": "object"
          },
          "label": "capacity",
          "order": 0,
          "type": "map"
        },
        "cephfs": {
          "fields": {
            "monitors": {
              "items": {
                "fields": {}
              },
              "label": "monitors",
              "order": 0
            },
            "path": {
              "label": "path",
              "order": 1,
              "type": "text"
            },
            "readOnly": {
              "label": "readOnly",
              "order": 5,
              "type": "text"
            },
            "secretFile": {
              "label": "secretFile",
              "order": 3,
              "type": "text"
            },
            "secretRef": {
              "fields": {
                "name": {
                  "label": "name",
                  "order": 0,
                  "type": "text"
                }
              },
              "label": "secretRef",
              "order": 4
            },
            "user": {
              "label": "user",
              "order": 2,
              "type": "text"
            }
          },
          "label": "cephfs",
          "order": 9
        },
        "cinder": {
          "fields": {
            "fsType": {
              "label": "fsType",
              "order": 1,
              "type": "text"
            },
            "readOnly": {
              "label": "readOnly",
              "order": 2,
              "type": "text"
            },
            "volumeID": {
              "label": "volumeID",
              "order": 0,
              "type": "text"
            }
          },
          "label": "cinder",
          "order": 8
        },
        "claimRef": {
          "fields": {
            "apiVersion": {
              "label": "apiVersion",
              "order": 4,
              "type": "text"
            },
            "fieldPath": {
              "label": "fieldPath",
              "order": 6,
              "type": "text"
            },
            "kind": {
              "label": "kind",
              "order": 0,
              "type": "text"
            },
            "name": {
              "label": "name",
              "order": 2,
              "type": "text"
            },
            "namespace": {
              "label": "namespace",
              "order": 1,
              "type": "text"
            },
            "resourceVersion": {
              "label": "resourceVersion",
              "order": 5,
              "type": "text"
            },
            "uid": {
              "label": "uid",
              "order": 3,
              "type": "text"
            }
          },
          "label": "claimRef",
          "order": 15
        },
        "fc": {
          "fields": {
            "fsType": {
              "label": "fsType",
              "order": 2,
              "type": "text"
            },
            "lun": {
              "label": "lun",
              "order": 1,
              "type": "text"
            },
            "readOnly": {
              "label": "readOnly",
              "order": 3,
              "type": "text"
            },
            "targetWWNs": {
              "items": {
                "fields": {}
              },
              "label": "targetWWNs",
              "order": 0
            }
          },
          "label": "fc",
          "order": 10
        },
        "flexVolume": {
          "fields": {
            "driver": {
              "label": "driver",
              "order": 0,
              "type": "text"
            },
            "fsType": {
              "label": "fsType",
              "order": 1,
              "type": "text"
            },
            "options": {
              "items": {
                "fields": {
                  "_key": {
                    "label": "key",
                    "type": "text"
                  },
                  "val": {
                    "label": "val",
                    "type": "text"
                  }
                },
                "type": "object"
              },
              "label": "options",
              "order": 4,
              "type": "map"
            },
            "readOnly": {
              "label": "readOnly",
              "order": 3,
              "type": "text"
            },
            "secretRef": {
              "fields": {
                "name": {
                  "label": "name",
                  "order": 0,
                  "type": "text"
                }
              },
              "label": "secretRef",
              "order": 2
            }
          },
          "label": "flexVolume",
          "order": 12
        },
        "flocker": {
          "fields": {
            "datasetName": {
              "label": "datasetName",
              "order": 0,
              "type": "text"
            }
          },
          "label": "flocker",
          "order": 11
        },
        "gcePersistentDisk": {
          "fields": {
            "fsType": {
              "label": "fsType",
              "order": 1,
              "type": "text"
            },
            "partition": {
              "label": "partition",
              "order": 2,
              "type": "text"
            },
            "pdName": {
              "label": "pdName",
              "order": 0,
              "type": "text"
            },
            "readOnly": {
              "label": "readOnly",
              "order": 3,
              "type": "text"
            }
          },
          "label": "gcePersistentDisk",
          "order": 1
        },
        "glusterfs": {
          "fields": {
            "endpoints": {
              "label": "endpoints",
              "order": 0,
              "type": "text"
            },
            "path": {
              "label": "path",
              "order": 1,
              "type": "text"
            },
            "readOnly": {
              "label": "readOnly",
              "order": 2,
              "type": "text"
            }
          },
          "label": "glusterfs",
          "order": 4
        },
        "hostPath": {
          "fields": {
            "path": {
              "label": "path",
              "order": 0,
              "type": "text"
            }
          },
          "label": "hostPath",
          "order": 3
        },
        "iscsi": {
          "fields": {
            "fsType": {
              "label": "fsType",
              "order": 4,
              "type": "text"
            },
            "iqn": {
              "label": "iqn",
              "order": 1,
              "type": "text"
            },
            "iscsiInterface": {
              "label": "iscsiInterface",
              "order": 3,
              "type": "text"
            },
            "lun": {
              "label": "lun",
              "order": 2,
              "type": "text"
            },
            "readOnly": {
              "label": "readOnly",
              "order": 5,
              "type": "text"
            },
            "targetPortal": {
              "label": "targetPortal",
              "order": 0,
              "type": "text"
            }
          },
          "label": "iscsi",
          "order": 7
        },
        "nfs": {
          "fields": {
            "path": {
              "label": "path",
              "order": 1,
              "type": "text"
            },
            "readOnly": {
              "label": "readOnly",
              "order": 2,
              "type": "text"
            },
            "server": {
              "label": "server",
              "order": 0,
              "type": "text"
            }
          },
          "label": "nfs",
          "order": 5
        },
        "persistentVolumeReclaimPolicy": {
          "label": "persistentVolumeReclaimPolicy",
          "order": 16,
          "type": "text"
        },
        "rbd": {
          "fields": {
            "fsType": {
              "label": "fsType",
              "order": 2,
              "type": "text"
            },
            "image": {
              "label": "image",
              "order": 1,
              "type": "text"
            },
            "keyring": {
              "label": "keyring",
              "order": 5,
              "type": "text"
            },
            "monitors": {
              "items": {
                "fields": {}
              },
              "label": "monitors",
              "order": 0
            },
            "pool": {
              "label": "pool",
              "order": 3,
              "type": "text"
            },
            "readOnly": {
              "label": "readOnly",
              "order": 7,
              "type": "text"
            },
            "secretRef": {
              "fields": {
                "name": {
                  "label": "name",
                  "order": 0,
                  "type": "text"
                }
              },
              "label": "secretRef",
              "order": 6
            },
            "user": {
              "label": "user",
              "order": 4,
              "type": "text"
            }
          },
          "label": "rbd",
          "order": 6
        }
      },
      "label": "spec",
      "order": 3
    }
  },
  "label": ""
}